{
  "basic": {
    "file_name": "Destroy Lonely - PASSAROUND.wav",
    "file_path": "/Users/jayden/SoundLens/tracks/Destroy Lonely/Destroy Lonely - PASSAROUND.wav",
    "sample_rate": 48000,
    "duration_seconds": 150.8600625,
    "bpm": 140.62,
    "key": "E Minor / Try A Minor",
    "key_note": "E",
    "key_mode": "Minor",
    "key_confidence": 56.00381151979857
  },
  "loudness": {
    "peak_db": 4.9700916982442346e-05,
    "rms_db": -10.398497917888674,
    "dynamic_range_db": 10.398547618805656,
    "clipping_detected": true,
    "clipping_samples": 1132,
    "clipping_percent": 0.01563258886581287,
    "headroom_db": -4.9700916982442346e-05
  },
  "frequency": {
    "band_percentages": {
      "Sub": 15.641314833309869,
      "Bass / 808": 15.629732083495346,
      "Mud": 14.333659602331739,
      "Low Mids": 14.151284947645046,
      "Mids / Melody": 13.959827525768825,
      "Harsh Zone": 13.266689318299237,
      "Highs": 14.092006352256714,
      "Air": 12.192174653434302,
      "Vocal Range": 14.884217479481013
    },
    "brightness_centroid_hz": 2805.872352342353,
    "brightness_label": "Medium",
    "spectral_rolloff_hz": 5835.930871747738,
    "dominant_band": "Sub",
    "low_end_total_percent": 31.271046916805215,
    "mid_total_percent": 42.44477207574561,
    "top_total_percent": 26.284181005691018
  },
  "fingerprint": {
    "mfcc_1": -154.13816833496094,
    "mfcc_2": 137.7984161376953,
    "mfcc_3": 6.1596455574035645,
    "mfcc_4": 64.48400115966797,
    "mfcc_5": -20.695161819458008,
    "mfcc_6": 34.65955352783203,
    "mfcc_7": 1.8618477582931519,
    "mfcc_8": 10.665948867797852,
    "mfcc_9": 2.099107027053833,
    "mfcc_10": 10.69497013092041,
    "mfcc_11": -3.053309440612793,
    "mfcc_12": 4.360884189605713,
    "mfcc_13": 0.4519115388393402,
    "chroma_1": 0.5349507331848145,
    "chroma_2": 0.43742597103118896,
    "chroma_3": 0.26421162486076355,
    "chroma_4": 0.24865232408046722,
    "chroma_5": 0.587290346622467,
    "chroma_6": 0.28393393754959106,
    "chroma_7": 0.33558881282806396,
    "chroma_8": 0.43080535531044006,
    "chroma_9": 0.23007653653621674,
    "chroma_10": 0.42089301347732544,
    "chroma_11": 0.21167872846126556,
    "chroma_12": 0.4003293812274933,
    "spectral_contrast": 19.47486157044588,
    "spectral_flatness": 0.0006419211276806891,
    "zero_crossing_rate": 0.04843816282522624
  },
  "rhythm": {
    "onset_count": 835,
    "onset_density": 5.534930757436217,
    "drum_activity": "High",
    "estimated_bars": 88,
    "seconds_per_bar": 1.7067273503057887
  },
  "sections": [
    {
      "name": "Intro",
      "start": 0.0,
      "end": 16.0,
      "avg_energy": 0.06280747056007385,
      "energy_label": "Low"
    },
    {
      "name": "Chorus / Hook",
      "start": 16.0,
      "end": 32.0,
      "avg_energy": 0.32208365201950073,
      "energy_label": "Medium"
    },
    {
      "name": "Verse",
      "start": 32.0,
      "end": 48.0,
      "avg_energy": 0.35131776332855225,
      "energy_label": "High"
    },
    {
      "name": "Chorus / Hook",
      "start": 48.0,
      "end": 64.0,
      "avg_energy": 0.34941530227661133,
      "energy_label": "High"
    },
    {
      "name": "Verse",
      "start": 64.0,
      "end": 80.0,
      "avg_energy": 0.2667372226715088,
      "energy_label": "Medium"
    },
    {
      "name": "Verse",
      "start": 80.0,
      "end": 96.0,
      "avg_energy": 0.28740882873535156,
      "energy_label": "Medium"
    },
    {
      "name": "Hook / Drop",
      "start": 96.0,
      "end": 112.0,
      "avg_energy": 0.34985852241516113,
      "energy_label": "High"
    },
    {
      "name": "Hook / Drop",
      "start": 112.0,
      "end": 128.0,
      "avg_energy": 0.343743234872818,
      "energy_label": "High"
    },
    {
      "name": "Outro",
      "start": 128.0,
      "end": 150.8600625,
      "avg_energy": 0.28085458278656006,
      "energy_label": "Medium"
    }
  ],
  "scores": {
    "mix": 86,
    "master": 86,
    "arrangement": 81,
    "release": 84,
    "energy": 7.300751041055663,
    "bass_strength": 6.254209383361043,
    "darkness": 4.388255295315293,
    "brightness": 5.611744704684707,
    "drum_bounce": 10,
    "vocal_space": 2.2449240236894408
  },
  "top_problems": [
    "Clipping detected: 1132 samples are near/over the limit.",
    "Mud range is elevated around 250-500 Hz.",
    "Intro may be long for short-form listener retention.",
    "Drum movement is very active; the beat could become overcrowded."
  ],
  "suggested_fixes": [
    "Lower the master/output, then use a soft clipper or limiter with safer ceiling.",
    "Gently cut 250-500 Hz on melodies, pads, or the master if the mix feels cloudy.",
    "Mute extra percussion in some sections so the hook/drop feels bigger.",
    "Consider bringing drums, 808, or a strong tag/moment in earlier."
  ],
  "artist_notes": [
    "Autotune/key starting point: E Minor / Try A Minor. Confidence: 56.0%.",
    "Beat energy: 7.3/10. Darkness: 4.4/10.",
    "Vocal space estimate: 2.2/10. Higher means easier space for vocals."
  ],
  "producer_notes": [
    "Low-end presence looks usable for the selected style.",
    "Selected style preset: rage_trap.",
    "Dominant frequency area: Sub.",
    "Drum activity is high at 5.53 hits/sec.",
    "Estimated length: 88 bars at 141 BPM."
  ],
  "master_notes": [
    "Clipping is the first thing to fix before judging the rest of the mix.",
    "Loudness is in a usable range for the selected style.",
    "Peak: 0.00 dB. RMS: -10.40 dB. Dynamic range: 10.40 dB."
  ],
  "next_steps": [
    "Lower the master/output, then use a soft clipper or limiter with safer ceiling.",
    "Gently cut 250-500 Hz on melodies, pads, or the master if the mix feels cloudy.",
    "Mute extra percussion in some sections so the hook/drop feels bigger.",
    "Fix the top 1-2 issues, export again, then re-run SoundLens."
  ]
}