{
  "basic": {
    "file_name": "Hardrock - Biggest Soldier.wav",
    "file_path": "/Users/jayden/SoundLens/tracks/Hardrock/Hardrock - Biggest Soldier.wav",
    "sample_rate": 48000,
    "duration_seconds": 139.92345833333334,
    "bpm": 152.03,
    "key": "C# Major",
    "key_note": "C#",
    "key_mode": "Major",
    "key_confidence": 48.48994032412635
  },
  "loudness": {
    "peak_db": -3.146520511953263,
    "rms_db": -14.193045281427672,
    "dynamic_range_db": 11.04652476947441,
    "clipping_detected": false,
    "clipping_samples": 0,
    "clipping_percent": 0.0,
    "headroom_db": 3.146520511953263
  },
  "frequency": {
    "band_percentages": {
      "Sub": 17.271930935117496,
      "Bass / 808": 15.04323287746895,
      "Mud": 14.04599870106724,
      "Low Mids": 14.167321579960198,
      "Mids / Melody": 14.24322184016046,
      "Harsh Zone": 13.399006468923258,
      "Highs": 13.490698722055738,
      "Air": 11.73759534221362,
      "Vocal Range": 15.008946463609668
    },
    "brightness_centroid_hz": 2203.774503867621,
    "brightness_label": "Medium",
    "spectral_rolloff_hz": 4698.752429867358,
    "dominant_band": "Sub",
    "low_end_total_percent": 32.31516381258645,
    "mid_total_percent": 42.4565421211879,
    "top_total_percent": 25.228294064269356
  },
  "fingerprint": {
    "mfcc_1": -232.69351196289062,
    "mfcc_2": 144.16799926757812,
    "mfcc_3": -7.254813194274902,
    "mfcc_4": 36.822513580322266,
    "mfcc_5": -4.150624752044678,
    "mfcc_6": 20.29414176940918,
    "mfcc_7": 1.5838074684143066,
    "mfcc_8": 11.506660461425781,
    "mfcc_9": 2.685696840286255,
    "mfcc_10": 3.949850082397461,
    "mfcc_11": 4.7153096199035645,
    "mfcc_12": 6.3425188064575195,
    "mfcc_13": 4.674338340759277,
    "chroma_1": 0.30052611231803894,
    "chroma_2": 0.5855680108070374,
    "chroma_3": 0.28294116258621216,
    "chroma_4": 0.261935830116272,
    "chroma_5": 0.3421608805656433,
    "chroma_6": 0.4605574607849121,
    "chroma_7": 0.3486996591091156,
    "chroma_8": 0.22576870024204254,
    "chroma_9": 0.2541307210922241,
    "chroma_10": 0.172580286860466,
    "chroma_11": 0.18034151196479797,
    "chroma_12": 0.1619144082069397,
    "spectral_contrast": 18.967465363663184,
    "spectral_flatness": 0.0005609833169728518,
    "zero_crossing_rate": 0.032011008549797985
  },
  "rhythm": {
    "onset_count": 627,
    "onset_density": 4.4810213202873115,
    "drum_activity": "High",
    "estimated_bars": 89,
    "seconds_per_bar": 1.5786357955666646
  },
  "sections": [
    {
      "name": "Section 1",
      "start": 0.0,
      "end": 12.629086364533316,
      "avg_energy": 0.19877596199512482,
      "energy_label": "High"
    },
    {
      "name": "Section 2",
      "start": 12.629086364533316,
      "end": 25.258172729066633,
      "avg_energy": 0.19604666531085968,
      "energy_label": "Medium"
    },
    {
      "name": "Section 3",
      "start": 25.258172729066633,
      "end": 37.88725909359995,
      "avg_energy": 0.17181815207004547,
      "energy_label": "Medium"
    },
    {
      "name": "Section 4",
      "start": 37.88725909359995,
      "end": 50.516345458133266,
      "avg_energy": 0.1554761677980423,
      "energy_label": "Low"
    },
    {
      "name": "Section 5",
      "start": 50.516345458133266,
      "end": 63.14543182266658,
      "avg_energy": 0.19489921629428864,
      "energy_label": "Medium"
    },
    {
      "name": "Section 6",
      "start": 63.14543182266658,
      "end": 75.7745181871999,
      "avg_energy": 0.16617707908153534,
      "energy_label": "Low"
    },
    {
      "name": "Section 7",
      "start": 75.7745181871999,
      "end": 88.40360455173322,
      "avg_energy": 0.044625841081142426,
      "energy_label": "Low"
    },
    {
      "name": "Section 8",
      "start": 88.40360455173322,
      "end": 101.03269091626655,
      "avg_energy": 0.23528297245502472,
      "energy_label": "High"
    },
    {
      "name": "Section 9",
      "start": 101.03269091626655,
      "end": 113.66177728079987,
      "avg_energy": 0.3070196807384491,
      "energy_label": "High"
    },
    {
      "name": "Section 10",
      "start": 113.66177728079987,
      "end": 126.29086364533319,
      "avg_energy": 0.24859637022018433,
      "energy_label": "High"
    },
    {
      "name": "Section 11",
      "start": 126.29086364533319,
      "end": 139.92345833333334,
      "avg_energy": 0.10209998488426208,
      "energy_label": "Low"
    }
  ],
  "scores": {
    "mix": 94,
    "master": 94,
    "arrangement": 81,
    "release": 90,
    "energy": 5.403477359286164,
    "bass_strength": 6.463032762517289,
    "darkness": 5.592450992264758,
    "brightness": 4.407549007735242,
    "drum_bounce": 10,
    "vocal_space": 2.3576974367216463
  },
  "stem_balance": null,
  "top_problems": [
    "Mud range is elevated around 250-500 Hz.",
    "Drum movement is very active; the beat could become overcrowded.",
    "Hook/verse contrast looks low, but arrangement detection is still an estimate."
  ],
  "suggested_fixes": [
    "Gently cut 250-500 Hz on melodies, pads, or the master if the mix feels cloudy.",
    "Mute extra percussion in some sections so the hook/drop feels bigger.",
    "Check the waveform/sections by ear. If the hook feels flat, add contrast with melody layers, drum changes, or vocal energy."
  ],
  "artist_notes": [
    "Autotune/key starting point: C# Major. Confidence: 48.5%.",
    "Beat energy: 5.4/10. Darkness: 5.6/10.",
    "Vocal space estimate: 2.4/10. Higher means easier space for vocals."
  ],
  "producer_notes": [
    "Low-end presence looks usable for the selected style.",
    "Selected style preset: rage_trap.",
    "Dominant frequency area: Sub.",
    "Drum activity is high at 4.48 hits/sec.",
    "Estimated length: 89 bars at 152 BPM."
  ],
  "master_notes": [
    "No obvious clipping problem detected.",
    "Loudness is in a usable range for the selected style.",
    "Peak: -3.15 dB. RMS: -14.19 dB. Dynamic range: 11.05 dB."
  ],
  "next_steps": [
    "Gently cut 250-500 Hz on melodies, pads, or the master if the mix feels cloudy.",
    "Mute extra percussion in some sections so the hook/drop feels bigger.",
    "Check the waveform/sections by ear. If the hook feels flat, add contrast with melody layers, drum changes, or vocal energy.",
    "This is close. Only make small changes unless you hear a clear problem."
  ]
}