{
  "basic": {
    "file_name": "Fimiguerrero - Dark Knight (feat. Lancey Foux).wav",
    "file_path": "/Users/jayden/SoundLens/tracks/Fimiguerrero/Fimiguerrero - Dark Knight (feat. Lancey Foux).wav",
    "sample_rate": 48000,
    "duration_seconds": 135.81485416666666,
    "bpm": 152.03,
    "key": "D Major",
    "key_note": "D",
    "key_mode": "Major",
    "key_confidence": 45.96610353598805
  },
  "loudness": {
    "peak_db": 0.0005943214993386505,
    "rms_db": -7.521052813843845,
    "dynamic_range_db": 7.5216471353431835,
    "clipping_detected": true,
    "clipping_samples": 34937,
    "clipping_percent": 0.5359164659363934,
    "headroom_db": -0.0005943214993386505
  },
  "frequency": {
    "band_percentages": {
      "Sub": 16.368091065961348,
      "Bass / 808": 14.676352094453115,
      "Mud": 14.35953148678589,
      "Low Mids": 14.342171226526098,
      "Mids / Melody": 14.209056568189368,
      "Harsh Zone": 13.791634097299744,
      "Highs": 13.7791846798926,
      "Air": 12.265612876454272,
      "Vocal Range": 15.086573155606231
    },
    "brightness_centroid_hz": 2897.297757501945,
    "brightness_label": "Medium",
    "spectral_rolloff_hz": 6298.502783122595,
    "dominant_band": "Sub",
    "low_end_total_percent": 31.044443160414463,
    "mid_total_percent": 42.910759281501356,
    "top_total_percent": 26.04479755634687
  },
  "fingerprint": {
    "mfcc_1": -96.94432067871094,
    "mfcc_2": 130.2643280029297,
    "mfcc_3": -12.11758041381836,
    "mfcc_4": 51.73332595825195,
    "mfcc_5": -13.663911819458008,
    "mfcc_6": 22.001089096069336,
    "mfcc_7": -2.8666138648986816,
    "mfcc_8": 11.961974143981934,
    "mfcc_9": 8.001160621643066,
    "mfcc_10": 9.177633285522461,
    "mfcc_11": 0.13002309203147888,
    "mfcc_12": 12.210807800292969,
    "mfcc_13": 1.4856138229370117,
    "chroma_1": 0.2055150270462036,
    "chroma_2": 0.29571616649627686,
    "chroma_3": 0.9502953290939331,
    "chroma_4": 0.37492620944976807,
    "chroma_5": 0.2433512955904007,
    "chroma_6": 0.18611033260822296,
    "chroma_7": 0.18524055182933807,
    "chroma_8": 0.17648044228553772,
    "chroma_9": 0.1817382425069809,
    "chroma_10": 0.2765747904777527,
    "chroma_11": 0.18124701082706451,
    "chroma_12": 0.15332411229610443,
    "spectral_contrast": 18.20127108552012,
    "spectral_flatness": 0.0012337547959759831,
    "zero_crossing_rate": 0.032689841050322
  },
  "rhythm": {
    "onset_count": 1092,
    "onset_density": 8.040357637611129,
    "drum_activity": "High",
    "estimated_bars": 86,
    "seconds_per_bar": 1.5786357955666646
  },
  "sections": [
    {
      "name": "Section 1",
      "start": 0.0,
      "end": 12.629086364533316,
      "avg_energy": 0.41819456219673157,
      "energy_label": "Low"
    },
    {
      "name": "Section 2",
      "start": 12.629086364533316,
      "end": 25.258172729066633,
      "avg_energy": 0.44682544469833374,
      "energy_label": "High"
    },
    {
      "name": "Section 3",
      "start": 25.258172729066633,
      "end": 37.88725909359995,
      "avg_energy": 0.4333629310131073,
      "energy_label": "Medium"
    },
    {
      "name": "Section 4",
      "start": 37.88725909359995,
      "end": 50.516345458133266,
      "avg_energy": 0.44543513655662537,
      "energy_label": "High"
    },
    {
      "name": "Section 5",
      "start": 50.516345458133266,
      "end": 63.14543182266658,
      "avg_energy": 0.4199375808238983,
      "energy_label": "Low"
    },
    {
      "name": "Section 6",
      "start": 63.14543182266658,
      "end": 75.7745181871999,
      "avg_energy": 0.4473499357700348,
      "energy_label": "High"
    },
    {
      "name": "Section 7",
      "start": 75.7745181871999,
      "end": 88.40360455173322,
      "avg_energy": 0.4446651041507721,
      "energy_label": "Medium"
    },
    {
      "name": "Section 8",
      "start": 88.40360455173322,
      "end": 101.03269091626655,
      "avg_energy": 0.4343554973602295,
      "energy_label": "Medium"
    },
    {
      "name": "Section 9",
      "start": 101.03269091626655,
      "end": 113.66177728079987,
      "avg_energy": 0.4230181574821472,
      "energy_label": "Low"
    },
    {
      "name": "Section 10",
      "start": 113.66177728079987,
      "end": 126.29086364533319,
      "avg_energy": 0.4448796510696411,
      "energy_label": "High"
    },
    {
      "name": "Section 11",
      "start": 126.29086364533319,
      "end": 135.81485416666666,
      "avg_energy": 0.0593695230782032,
      "energy_label": "Low"
    }
  ],
  "scores": {
    "mix": 81,
    "master": 81,
    "arrangement": 81,
    "release": 81,
    "energy": 8.739473593078078,
    "bass_strength": 6.208888632082893,
    "darkness": 4.2054044849961105,
    "brightness": 5.7945955150038895,
    "drum_bounce": 10,
    "vocal_space": 2.207305801496201
  },
  "stem_balance": null,
  "top_problems": [
    "Clipping detected: 34937 samples are near/over the limit.",
    "Mud range is elevated around 250-500 Hz.",
    "Drum movement is very active; the beat could become overcrowded.",
    "Hook/verse contrast looks low, but arrangement detection is still an estimate."
  ],
  "suggested_fixes": [
    "Lower the master/output, then use a soft clipper or limiter with safer ceiling.",
    "Gently cut 250-500 Hz on melodies, pads, or the master if the mix feels cloudy.",
    "Mute extra percussion in some sections so the hook/drop feels bigger.",
    "Check the waveform/sections by ear. If the hook feels flat, add contrast with melody layers, drum changes, or vocal energy."
  ],
  "artist_notes": [
    "Autotune/key starting point: D Major. Confidence: 46.0%.",
    "Beat energy: 8.7/10. Darkness: 4.2/10.",
    "Vocal space estimate: 2.2/10. Higher means easier space for vocals."
  ],
  "producer_notes": [
    "Low-end presence looks usable for the selected style.",
    "Selected style preset: rage_trap.",
    "Dominant frequency area: Sub.",
    "Drum activity is high at 8.04 hits/sec.",
    "Estimated length: 86 bars at 152 BPM."
  ],
  "master_notes": [
    "Clipping is the first thing to fix before judging the rest of the mix.",
    "Loudness is in a usable range for the selected style.",
    "Peak: 0.00 dB. RMS: -7.52 dB. Dynamic range: 7.52 dB."
  ],
  "next_steps": [
    "Lower the master/output, then use a soft clipper or limiter with safer ceiling.",
    "Gently cut 250-500 Hz on melodies, pads, or the master if the mix feels cloudy.",
    "Mute extra percussion in some sections so the hook/drop feels bigger.",
    "Fix the top 1-2 issues, export again, then re-run SoundLens."
  ]
}