{
  "basic": {
    "file_name": "Midwxst - s.f.b.wav",
    "file_path": "/Users/jayden/SoundLens/tracks/Midwxst/Midwxst - s.f.b.wav",
    "sample_rate": 48000,
    "duration_seconds": 168.12502083333334,
    "bpm": 148.03,
    "key": "D Minor",
    "key_note": "D",
    "key_mode": "Minor",
    "key_confidence": 46.246632480687126
  },
  "loudness": {
    "peak_db": 0.00011493293894066517,
    "rms_db": -9.601688495192255,
    "dynamic_range_db": 9.601803428131195,
    "clipping_detected": true,
    "clipping_samples": 29693,
    "clipping_percent": 0.36794295316692033,
    "headroom_db": -0.00011493293894066517
  },
  "frequency": {
    "band_percentages": {
      "Sub": 15.788857131586367,
      "Bass / 808": 15.078063181351261,
      "Mud": 14.27064644705901,
      "Low Mids": 14.483019164406846,
      "Mids / Melody": 14.37276374203385,
      "Harsh Zone": 13.832867177033723,
      "Highs": 13.589782775757003,
      "Air": 12.416867556080696,
      "Vocal Range": 15.14261710438159
    },
    "brightness_centroid_hz": 3224.803890278312,
    "brightness_label": "Medium",
    "spectral_rolloff_hz": 6975.766975161781,
    "dominant_band": "Sub",
    "low_end_total_percent": 30.86692031293763,
    "mid_total_percent": 43.1264293534997,
    "top_total_percent": 26.006650331837697
  },
  "fingerprint": {
    "mfcc_1": -109.41495513916016,
    "mfcc_2": 126.15837097167969,
    "mfcc_3": -27.137203216552734,
    "mfcc_4": 45.99139404296875,
    "mfcc_5": -16.988039016723633,
    "mfcc_6": 26.01636505126953,
    "mfcc_7": -4.2099995613098145,
    "mfcc_8": 6.320652484893799,
    "mfcc_9": 0.08183979988098145,
    "mfcc_10": 2.296924352645874,
    "mfcc_11": 6.170233726501465,
    "mfcc_12": 3.4110841751098633,
    "mfcc_13": 4.5494890213012695,
    "chroma_1": 0.44535794854164124,
    "chroma_2": 0.38031384348869324,
    "chroma_3": 0.6049745678901672,
    "chroma_4": 0.5368972420692444,
    "chroma_5": 0.3918915092945099,
    "chroma_6": 0.4431532919406891,
    "chroma_7": 0.38294845819473267,
    "chroma_8": 0.4835819602012634,
    "chroma_9": 0.38568928837776184,
    "chroma_10": 0.45792311429977417,
    "chroma_11": 0.44482702016830444,
    "chroma_12": 0.37045493721961975,
    "spectral_contrast": 19.446049118082726,
    "spectral_flatness": 0.0010859562316909432,
    "zero_crossing_rate": 0.05876936644501015
  },
  "rhythm": {
    "onset_count": 685,
    "onset_density": 4.074348937503229,
    "drum_activity": "High",
    "estimated_bars": 104,
    "seconds_per_bar": 1.621292981152469
  },
  "sections": [
    {
      "name": "Intro",
      "start": 0.0,
      "end": 16.0,
      "avg_energy": 0.29778003692626953,
      "energy_label": "Medium"
    },
    {
      "name": "Chorus / Hook",
      "start": 16.0,
      "end": 32.0,
      "avg_energy": 0.4373527765274048,
      "energy_label": "High"
    },
    {
      "name": "Verse",
      "start": 32.0,
      "end": 48.0,
      "avg_energy": 0.3615292012691498,
      "energy_label": "Medium"
    },
    {
      "name": "Chorus / Hook",
      "start": 48.0,
      "end": 64.0,
      "avg_energy": 0.37431877851486206,
      "energy_label": "High"
    },
    {
      "name": "Verse",
      "start": 64.0,
      "end": 80.0,
      "avg_energy": 0.413204550743103,
      "energy_label": "High"
    },
    {
      "name": "Bridge / Breakdown",
      "start": 80.0,
      "end": 96.0,
      "avg_energy": 0.26367831230163574,
      "energy_label": "Low"
    },
    {
      "name": "Verse",
      "start": 96.0,
      "end": 112.0,
      "avg_energy": 0.36126765608787537,
      "energy_label": "Medium"
    },
    {
      "name": "Hook / Drop",
      "start": 112.0,
      "end": 128.0,
      "avg_energy": 0.4240556061267853,
      "energy_label": "High"
    },
    {
      "name": "Bridge / Breakdown",
      "start": 128.0,
      "end": 144.0,
      "avg_energy": 0.20536577701568604,
      "energy_label": "Low"
    },
    {
      "name": "Outro",
      "start": 144.0,
      "end": 168.12502083333334,
      "avg_energy": 0.07359101623296738,
      "energy_label": "Low"
    }
  ],
  "scores": {
    "mix": 81,
    "master": 81,
    "arrangement": 75,
    "release": 79,
    "energy": 7.699155752403873,
    "bass_strength": 6.173384062587526,
    "darkness": 3.550392219443376,
    "brightness": 6.449607780556624,
    "drum_bounce": 10,
    "vocal_space": 2.222738683403989
  },
  "stem_balance": null,
  "top_problems": [
    "Clipping detected: 29693 samples are near/over the limit.",
    "Mud range is elevated around 250-500 Hz.",
    "Intro may be long for short-form listener retention.",
    "Drum movement is very active; the beat could become overcrowded.",
    "Hook/verse contrast looks low, but arrangement detection is still an estimate."
  ],
  "suggested_fixes": [
    "Lower the master/output, then use a soft clipper or limiter with safer ceiling.",
    "Gently cut 250-500 Hz on melodies, pads, or the master if the mix feels cloudy.",
    "Mute extra percussion in some sections so the hook/drop feels bigger.",
    "Check the waveform/sections by ear. If the hook feels flat, add contrast with melody layers, drum changes, or vocal energy.",
    "Consider bringing drums, 808, or a strong tag/moment in earlier."
  ],
  "artist_notes": [
    "Autotune/key starting point: D Minor. Confidence: 46.2%.",
    "Beat energy: 7.7/10. Darkness: 3.6/10.",
    "Vocal space estimate: 2.2/10. Higher means easier space for vocals."
  ],
  "producer_notes": [
    "Low-end presence looks usable for the selected style.",
    "Selected style preset: rage_trap.",
    "Dominant frequency area: Sub.",
    "Drum activity is high at 4.07 hits/sec.",
    "Estimated length: 104 bars at 148 BPM."
  ],
  "master_notes": [
    "Clipping is the first thing to fix before judging the rest of the mix.",
    "Loudness is in a usable range for the selected style.",
    "Peak: 0.00 dB. RMS: -9.60 dB. Dynamic range: 9.60 dB."
  ],
  "next_steps": [
    "Lower the master/output, then use a soft clipper or limiter with safer ceiling.",
    "Gently cut 250-500 Hz on melodies, pads, or the master if the mix feels cloudy.",
    "Mute extra percussion in some sections so the hook/drop feels bigger.",
    "Fix the top 1-2 issues, export again, then re-run SoundLens."
  ]
}