{
  "basic": {
    "file_name": "Slayr - Find Me Again.wav",
    "file_path": "/Users/jayden/SoundLens/tracks/Slayr/Slayr - Find Me Again.wav",
    "sample_rate": 48000,
    "duration_seconds": 166.13839583333333,
    "bpm": 140.62,
    "key": "D# Minor",
    "key_note": "D#",
    "key_mode": "Minor",
    "key_confidence": 46.19073737420399
  },
  "loudness": {
    "peak_db": 0.0015644070350027185,
    "rms_db": -9.110774227960125,
    "dynamic_range_db": 9.112338634995128,
    "clipping_detected": true,
    "clipping_samples": 58247,
    "clipping_percent": 0.7304026023484688,
    "headroom_db": -0.0015644070350027185
  },
  "frequency": {
    "band_percentages": {
      "Sub": 15.471117760930673,
      "Bass / 808": 14.810024657412052,
      "Mud": 14.576734197603516,
      "Low Mids": 15.007029835226692,
      "Mids / Melody": 14.674852246273263,
      "Harsh Zone": 14.011919541363868,
      "Highs": 13.107478458475558,
      "Air": 12.352762842369694,
      "Vocal Range": 15.562939777914018
    },
    "brightness_centroid_hz": 3031.9194848753605,
    "brightness_label": "Medium",
    "spectral_rolloff_hz": 6228.244775616333,
    "dominant_band": "Sub",
    "low_end_total_percent": 30.281142418342725,
    "mid_total_percent": 44.25861627910347,
    "top_total_percent": 25.460241300845254
  },
  "fingerprint": {
    "mfcc_1": -65.89041900634766,
    "mfcc_2": 148.37606811523438,
    "mfcc_3": -22.70759391784668,
    "mfcc_4": 18.228853225708008,
    "mfcc_5": -7.398225784301758,
    "mfcc_6": 13.8040771484375,
    "mfcc_7": -15.692562103271484,
    "mfcc_8": 8.787919044494629,
    "mfcc_9": -3.048973560333252,
    "mfcc_10": 4.299651622772217,
    "mfcc_11": -4.378190517425537,
    "mfcc_12": 5.493431091308594,
    "mfcc_13": -4.399384498596191,
    "chroma_1": 0.3879190683364868,
    "chroma_2": 0.39313411712646484,
    "chroma_3": 0.34177523851394653,
    "chroma_4": 0.5072739124298096,
    "chroma_5": 0.302897572517395,
    "chroma_6": 0.469470351934433,
    "chroma_7": 0.4272031784057617,
    "chroma_8": 0.3074532449245453,
    "chroma_9": 0.36462265253067017,
    "chroma_10": 0.32572370767593384,
    "chroma_11": 0.5524996519088745,
    "chroma_12": 0.532525897026062,
    "spectral_contrast": 19.081734432349073,
    "spectral_flatness": 0.0023929246235638857,
    "zero_crossing_rate": 0.059642570350619546
  },
  "rhythm": {
    "onset_count": 690,
    "onset_density": 4.153163972355879,
    "drum_activity": "High",
    "estimated_bars": 97,
    "seconds_per_bar": 1.7067273503057887
  },
  "sections": [
    {
      "name": "Intro",
      "start": 0.0,
      "end": 16.0,
      "avg_energy": 0.24252267181873322,
      "energy_label": "Low"
    },
    {
      "name": "Chorus / Hook",
      "start": 16.0,
      "end": 32.0,
      "avg_energy": 0.31820744276046753,
      "energy_label": "Medium"
    },
    {
      "name": "Verse",
      "start": 32.0,
      "end": 48.0,
      "avg_energy": 0.4808236360549927,
      "energy_label": "High"
    },
    {
      "name": "Chorus / Hook",
      "start": 48.0,
      "end": 64.0,
      "avg_energy": 0.37146249413490295,
      "energy_label": "Medium"
    },
    {
      "name": "Verse",
      "start": 64.0,
      "end": 80.0,
      "avg_energy": 0.2620135545730591,
      "energy_label": "Low"
    },
    {
      "name": "Verse",
      "start": 80.0,
      "end": 96.0,
      "avg_energy": 0.32399073243141174,
      "energy_label": "Medium"
    },
    {
      "name": "Verse",
      "start": 96.0,
      "end": 112.0,
      "avg_energy": 0.36125656962394714,
      "energy_label": "Medium"
    },
    {
      "name": "Verse",
      "start": 112.0,
      "end": 128.0,
      "avg_energy": 0.38644537329673767,
      "energy_label": "Medium"
    },
    {
      "name": "Hook / Drop",
      "start": 128.0,
      "end": 144.0,
      "avg_energy": 0.5065774917602539,
      "energy_label": "High"
    },
    {
      "name": "Outro",
      "start": 144.0,
      "end": 166.13839583333333,
      "avg_energy": 0.1589670181274414,
      "energy_label": "Low"
    }
  ],
  "scores": {
    "mix": 81,
    "master": 81,
    "arrangement": 81,
    "release": 81,
    "energy": 7.944612886019938,
    "bass_strength": 6.056228483668545,
    "darkness": 3.936161030249279,
    "brightness": 6.063838969750721,
    "drum_bounce": 10,
    "vocal_space": 2.025444915926209
  },
  "stem_balance": null,
  "top_problems": [
    "Clipping detected: 58247 samples are near/over the limit.",
    "Mud range is elevated around 250-500 Hz.",
    "Intro may be long for short-form listener retention.",
    "Drum movement is very active; the beat could become overcrowded."
  ],
  "suggested_fixes": [
    "Lower the master/output, then use a soft clipper or limiter with safer ceiling.",
    "Gently cut 250-500 Hz on melodies, pads, or the master if the mix feels cloudy.",
    "Mute extra percussion in some sections so the hook/drop feels bigger.",
    "Consider bringing drums, 808, or a strong tag/moment in earlier."
  ],
  "artist_notes": [
    "Autotune/key starting point: D# Minor. Confidence: 46.2%.",
    "Beat energy: 7.9/10. Darkness: 3.9/10.",
    "Vocal space estimate: 2.0/10. Higher means easier space for vocals."
  ],
  "producer_notes": [
    "Low-end presence looks usable for the selected style.",
    "Selected style preset: rage_trap.",
    "Dominant frequency area: Sub.",
    "Drum activity is high at 4.15 hits/sec.",
    "Estimated length: 97 bars at 141 BPM."
  ],
  "master_notes": [
    "Clipping is the first thing to fix before judging the rest of the mix.",
    "Loudness is in a usable range for the selected style.",
    "Peak: 0.00 dB. RMS: -9.11 dB. Dynamic range: 9.11 dB."
  ],
  "next_steps": [
    "Lower the master/output, then use a soft clipper or limiter with safer ceiling.",
    "Gently cut 250-500 Hz on melodies, pads, or the master if the mix feels cloudy.",
    "Mute extra percussion in some sections so the hook/drop feels bigger.",
    "Fix the top 1-2 issues, export again, then re-run SoundLens."
  ]
}